tests/__init__.py
tests/test_blackbody_flux.py
tests/test_transformer_payne.py
transformer_payne/__init__.py
transformer_payne/_utility.py
transformer_payne/architecture_definition.py
transformer_payne/blackbody.py
transformer_payne/configuration.py
transformer_payne/download.py
transformer_payne/exceptions.py
transformer_payne/huggingface_config.py
transformer_payne/spectrum_emulator.py
transformer_payne/transformer_payne.py
transformer_payne-0.10.dist-info/METADATA
transformer_payne-0.10.dist-info/WHEEL
transformer_payne-0.10.dist-info/top_level.txt
transformer_payne-0.10.dist-info/RECORD
