Metadata-Version: 2.4
Name: transformer_payne
Version: 0.10
Requires-Dist: jax>=0.4.38
Requires-Dist: jaxlib>=0.4.38
Requires-Dist: numpy~=1.26.4
Requires-Dist: flax<=0.10.6
Requires-Dist: joblib~=1.3.2
Provides-Extra: huggingface
Requires-Dist: huggingface-hub~=0.21.3; extra == "huggingface"
Provides-Extra: dev
Requires-Dist: pytest~=8.0.0; extra == "dev"
Requires-Dist: pytest-datadir~=1.5.0; extra == "dev"
Requires-Dist: coverage~=7.4.3; extra == "dev"
